[
  {
    "title": "mCGCNN: A Dual-Stream Crystal Graph Convolutional Neural Network for the Efficient Prediction of Magnetic Properties of Crystalline Materials",
    "title_zh": "mCGCNN：用于高效预测晶体材料磁性质的双流晶体图卷积神经网络",
    "summary": "",
    "abstract": "",
    "category": "AI×化学·材料",
    "link": "https://arxiv.org/abs/2606.28458",
    "journal": "arXiv"
  },
  {
    "title": "Seismic full waveform inversion via a physics-guided Fourier representation neural network",
    "title_zh": "基于物理引导傅里叶表示神经网络的地震全波形反演",
    "summary": "",
    "abstract": "",
    "category": "AI×物理",
    "link": "https://arxiv.org/abs/2606.30126",
    "journal": "arXiv"
  },
  {
    "title": "Verified residual-specific explicit derivative kernels for physics-informed learning and discretized PDE adjoints",
    "title_zh": "面向物理信息学习与离散 PDE 伴随的经验证残差专用显式导数核",
    "summary": "",
    "abstract": "",
    "category": "AI×物理",
    "link": "https://arxiv.org/abs/2606.29702",
    "journal": "arXiv"
  },
  {
    "title": "Physics-Informed Neural Quantum Control for Extended Rovibrational Photoassociation in a Morse Molecular System",
    "title_zh": "",
    "summary": "",
    "abstract": "",
    "category": "AI×物理",
    "link": "https://arxiv.org/abs/2606.29610",
    "journal": "arXiv"
  }
]